MANIFEST.in
README.rst
setup.py
demo/run_server.py
py_summer.egg-info/PKG-INFO
py_summer.egg-info/SOURCES.txt
py_summer.egg-info/dependency_links.txt
py_summer.egg-info/entry_points.txt
py_summer.egg-info/requires.txt
py_summer.egg-info/top_level.txt
summer/__init__.py
summer/app.py
summer/command.py
summer/config.py
summer/models.py
summer/tpl/.gitignore.tpl
summer/tpl/__init__.tpl
summer/tpl/config.json
summer/tpl/config.tpl
summer/tpl/conftest.tpl
summer/tpl/docker-compose.tpl
summer/tpl/error.tpl
summer/tpl/gunicorn.tpl
summer/tpl/hello_controller.tpl
summer/tpl/hello_handler.tpl
summer/tpl/requirements.tpl
summer/tpl/router.tpl
summer/tpl/server.tpl
summer/tpl/start.tpl
summer/tpl/test_api.tpl
summer/tpl/test_db.tpl
summer/tpl/user_model.tpl
test/__init__.py
test/conftest.py
test/test_db.py
test/test_summer.py