Metadata-Version: 1.1
Name: py-summer
Version: 0.0.2
Summary: 一个快速生成 Python Web 项目框架的工具
Home-page: https://github.com/chinapnr/py-summer
Author: David Yi
Author-email: wingfish@gmail.com
License: MIT
Platform: UNKNOWN
Classifier: Development Status :: 4 - Beta
Classifier: Intended Audience :: Developers
Classifier: Topic :: Software Development :: Build Tools
Classifier: License :: OSI Approved :: MIT License
Classifier: Programming Language :: Python
Classifier: Programming Language :: Python :: 3.6
Classifier: Programming Language :: Python :: 3.7
